MANIFEST.in
README.md
setup.cfg
setup.py
ashapcott_surveymonty.egg-info/PKG-INFO
ashapcott_surveymonty.egg-info/SOURCES.txt
ashapcott_surveymonty.egg-info/dependency_links.txt
ashapcott_surveymonty.egg-info/requires.txt
ashapcott_surveymonty.egg-info/top_level.txt
surveymonty/VERSION
surveymonty/__init__.py
surveymonty/client.py
surveymonty/constants.py
surveymonty/exceptions.py
surveymonty/signals.py
surveymonty/utils.py
surveymonty/versions/__init__.py
surveymonty/versions/client_v3.py
surveymonty/versions/v3.json
tests/__init__.py
tests/integration/__init__.py
tests/integration/test_api.py
tests/unit/__init__.py
tests/unit/test_client.py
tests/unit/test_utils.py