Metadata-Version: 1.0
Name: ashapcott-surveymonty
Version: 0.3.1
Summary: Python wrapper for SurveyMonkey API
Home-page: https://github.com/AshtonShapcott/SurveyMonty
Author: Ashton Shapcott
Author-email: ashapcott@gmail.com
License: MIT
Keywords: SurveyMonkey
Platform: UNKNOWN
